mwapi/__init__.py
mwapi/about.py
mwapi/async_session.py
mwapi/cli.py
mwapi/errors.py
mwapi/session.py
mwapi/util.py
mwapi-0.6.1.dist-info/LICENSE
mwapi-0.6.1.dist-info/METADATA
mwapi-0.6.1.dist-info/WHEEL
mwapi-0.6.1.dist-info/top_level.txt
mwapi-0.6.1.dist-info/RECORD
