Metadata-Version: 2.1
Name: mwapi
Version: 0.6.1
Summary: Simple wrapper for the Mediawiki API
Home-page: https://github.com/mediawiki-utilities/python-mwapi
Author: Aaron Halfaker
Author-email: aaron.halfaker@gmail.com
License: MIT
Platform: UNKNOWN
Requires-Dist: aiohttp
Requires-Dist: requests
